pflogger/__init__.py
pflogger-1.0.0.dist-info/DESCRIPTION.rst
pflogger-1.0.0.dist-info/METADATA
pflogger-1.0.0.dist-info/RECORD
pflogger-1.0.0.dist-info/WHEEL
pflogger-1.0.0.dist-info/metadata.json
pflogger-1.0.0.dist-info/top_level.txt
