Metadata-Version: 2.0
Name: pflogger
Version: 1.0.0
Summary: Configuration of python logging handler for Perfee.
Home-page: https://github.com/perfeelab/pflogger
Author: ClaireHuang
Author-email: clairehf@163.com
License: UNKNOWN
Platform: UNKNOWN
Classifier: Programming Language :: Python :: 2
Classifier: Programming Language :: Python :: 3
Classifier: License :: OSI Approved :: MIT License
Classifier: Operating System :: OS Independent
